cdk_private_asset_bucket/__init__.py
cdk_private_asset_bucket/py.typed
cdk_private_asset_bucket/_jsii/__init__.py
cdk_private_asset_bucket/_jsii/cdk-private-asset-bucket@2.25.0.jsii.tgz
cdk_private_asset_bucket-2.25.0.dist-info/LICENSE
cdk_private_asset_bucket-2.25.0.dist-info/METADATA
cdk_private_asset_bucket-2.25.0.dist-info/WHEEL
cdk_private_asset_bucket-2.25.0.dist-info/top_level.txt
cdk_private_asset_bucket-2.25.0.dist-info/RECORD
