Metadata-Version: 2.1
Name: cdk-private-asset-bucket
Version: 2.25.0
Summary: Construct to create a private asset S3 bucket. A cognito token can be used to allow access to he S3 asset.
Home-page: https://github.com/mmuller88/cdk-private-asset-bucket
Author: Martin Mueller https://martinmueller.dev/resume<damadden88@googlemail.com>
License: Apache-2.0
Project-URL: Source, https://github.com/mmuller88/cdk-private-asset-bucket
Platform: UNKNOWN
Classifier: Intended Audience :: Developers
Classifier: Operating System :: OS Independent
Classifier: Programming Language :: JavaScript
Classifier: Programming Language :: Python :: 3 :: Only
Classifier: Programming Language :: Python :: 3.6
Classifier: Programming Language :: Python :: 3.7
Classifier: Programming Language :: Python :: 3.8
Classifier: Programming Language :: Python :: 3.9
Classifier: Typing :: Typed
Classifier: Development Status :: 5 - Production/Stable
Classifier: License :: OSI Approved
Requires-Python: >=3.6
License-File: LICENSE
Requires-Dist: aws-cdk-lib (<3.0.0,>=2.21.0)
Requires-Dist: constructs (<11.0.0,>=10.0.5)
Requires-Dist: jsii (<2.0.0,>=1.56.0)
Requires-Dist: publication (>=0.0.3)
